heaserver/storage/__init__.py
heaserver/storage/service.py
heaserver/storage/wstl/all.json
heaserver_storage-1.1.1.dist-info/LICENSE
heaserver_storage-1.1.1.dist-info/METADATA
heaserver_storage-1.1.1.dist-info/WHEEL
heaserver_storage-1.1.1.dist-info/entry_points.txt
heaserver_storage-1.1.1.dist-info/top_level.txt
heaserver_storage-1.1.1.dist-info/RECORD
