Metadata-Version: 2.1
Name: heaserver-storage
Version: 1.1.1
Summary: a service manages storage information details
Home-page: https://risr.hci.utah.edu
Author: Research Informatics Shared Resource, Huntsman Cancer Institute, Salt Lake City, UT
Author-email: Andrew.Post@hci.utah.edu
Keywords: heaserver-storage,microservice,healthcare,cancer,research,informatics
Classifier: Development Status :: 5 - Production/Stable
Classifier: Intended Audience :: Developers
Classifier: Intended Audience :: Science/Research
Classifier: License :: OSI Approved :: Apache Software License
Classifier: Framework :: AsyncIO
Classifier: Environment :: Web Environment
Classifier: Natural Language :: English
Classifier: Operating System :: OS Independent
Classifier: Programming Language :: Python :: 3
Classifier: Programming Language :: Python :: 3.10
Classifier: Programming Language :: Python :: 3.11
Classifier: Programming Language :: Python :: 3.12
Classifier: Topic :: Software Development
Classifier: Topic :: Scientific/Engineering
Classifier: Topic :: Scientific/Engineering :: Bio-Informatics
Classifier: Topic :: Scientific/Engineering :: Information Analysis
Classifier: Topic :: Scientific/Engineering :: Medical Science Apps.
Requires-Python: >=3.10
License-File: LICENSE
Requires-Dist: heaserver~=1.18.0
